{
  "moduleId": "SparkFun-PowerIC-V_REG_MIC5235-",
  "title": "V_REG_MIC5235",
  "sourceFzp": "vendor_reference\\fritzing_official\\fritzing-parts\\core\\sparkfun-poweric-v_reg_mic5235-.fzp",
  "copiedViews": [
    {
      "view": "breadboard",
      "source": "vendor_reference\\fritzing_official\\fritzing-parts\\svg\\core\\breadboard\\sparkfun-poweric_sot23-5_breadboard.svg",
      "file": "breadboard.svg"
    },
    {
      "view": "schematic",
      "source": "vendor_reference\\fritzing_official\\fritzing-parts\\svg\\core\\schematic\\sparkfun-poweric_v-reg-ldo-adj_schematic.svg",
      "file": "schematic.svg"
    },
    {
      "view": "pcb",
      "source": "vendor_reference\\fritzing_official\\fritzing-parts\\svg\\core\\pcb\\sparkfun-poweric_sot23-5_pcb.svg",
      "file": "pcb.svg"
    },
    {
      "view": "icon",
      "source": "vendor_reference\\fritzing_official\\fritzing-parts\\svg\\core\\breadboard\\sparkfun-poweric_sot23-5_breadboard.svg",
      "file": "icon.svg"
    }
  ],
  "missingViews": [],
  "connectorCount": 5,
  "connectors": [
    {
      "id": "connector3",
      "type": "male",
      "name": "ADJ",
      "description": "ADJ"
    },
    {
      "id": "connector2",
      "type": "male",
      "name": "EN",
      "description": "EN"
    },
    {
      "id": "connector1",
      "type": "male",
      "name": "GND",
      "description": "GND"
    },
    {
      "id": "connector0",
      "type": "male",
      "name": "IN",
      "description": "IN"
    },
    {
      "id": "connector4",
      "type": "male",
      "name": "OUT",
      "description": "OUT"
    }
  ]
}