{
  "moduleId": "1001ABDC03F",
  "title": "Electrolytic Capacitor",
  "sourceFzp": "vendor_reference\\fritzing_official\\fritzing-parts\\obsolete\\electrolytic_capacitor_100uF.fzp",
  "copiedViews": [
    {
      "view": "icon",
      "source": "vendor_reference\\fritzing_official\\fritzing-parts\\svg\\obsolete\\icon\\electrolytic_capacitor_100uF_icon.svg",
      "file": "icon.svg"
    },
    {
      "view": "schematic",
      "source": "vendor_reference\\fritzing_official\\fritzing-parts\\svg\\core\\schematic\\capacitor_polar.svg",
      "file": "schematic.svg"
    },
    {
      "view": "pcb",
      "source": "vendor_reference\\fritzing_official\\fritzing-parts\\svg\\obsolete\\pcb\\radial_can_200mil.svg",
      "file": "pcb.svg"
    }
  ],
  "missingViews": [],
  "connectorCount": 2,
  "connectors": [
    {
      "id": "connector0",
      "type": "male",
      "name": "-",
      "description": "- side"
    },
    {
      "id": "connector1",
      "type": "male",
      "name": "+",
      "description": "+ side"
    }
  ]
}